adjusted_identity/__init__.py
adjusted_identity-0.2.5.dist-info/licenses/LICENSE
tests/__init__.py
tests/compare_versions.py
tests/test_alignment.py
tests/test_gap_adjustment.py
tests/test_head_comparison.py
tests/test_metric_baseline.py
tests/test_score_alignment.py
tests/test_spec_compliance.py
tests/test_spec_generated.py
tests/test_unified_architecture.py
tests/test_utilities.py
adjusted_identity-0.2.5.dist-info/METADATA
adjusted_identity-0.2.5.dist-info/WHEEL
adjusted_identity-0.2.5.dist-info/top_level.txt
adjusted_identity-0.2.5.dist-info/RECORD
