Metadata-Version: 2.4
Name: adjusted-identity
Version: 0.2.5
Summary: Adjusted Identity Calculator for DNA Sequences with MycoBLAST-style preprocessing and MSA support
Home-page: https://github.com/joshuaowalker/adjusted-identity
Author: Josh Walker
Author-email: Josh Walker <joshowalker@yahoo.com>
License: BSD 2-Clause License
Project-URL: Homepage, https://github.com/joshuaowalker/adjusted-identity
Project-URL: Bug Reports, https://github.com/joshuaowalker/adjusted-identity/issues
Project-URL: Source, https://github.com/joshuaowalker/adjusted-identity
Keywords: bioinformatics,dna,sequence,alignment,mycology,identity,barcode,MycoBLAST,ITS
Classifier: Development Status :: 4 - Beta
Classifier: Intended Audience :: Science/Research
Classifier: Topic :: Scientific/Engineering :: Bio-Informatics
Classifier: Programming Language :: Python :: 3
Classifier: Programming Language :: Python :: 3.8
Classifier: Programming Language :: Python :: 3.9
Classifier: Programming Language :: Python :: 3.10
Classifier: Programming Language :: Python :: 3.11
Classifier: Programming Language :: Python :: 3.12
Classifier: Programming Language :: Python :: 3.13
Requires-Python: >=3.8
License-File: LICENSE
Requires-Dist: edlib>=1.3.9
Provides-Extra: dev
Requires-Dist: pytest>=7.0.0; extra == "dev"
Requires-Dist: pytest-cov>=4.0.0; extra == "dev"
Dynamic: author
Dynamic: home-page
Dynamic: license-file
Dynamic: requires-python
